sas_comm_py/__init__.py
sas_comm_py/crc.py
sas_comm_py-0.1.0.dist-info/licenses/LICENSE
sas_comm_py-0.1.0.dist-info/METADATA
sas_comm_py-0.1.0.dist-info/WHEEL
sas_comm_py-0.1.0.dist-info/top_level.txt
sas_comm_py-0.1.0.dist-info/RECORD
