Metadata-Version: 2.4
Name: sas_comm_py
Version: 0.1.0
Summary: Python library to communicate with slot machines using serial port
Home-page: https://github.com/mdedz/sas_comm_py
Author: Mayled
Author-email: mayleddev88@gmail.com
Classifier: Programming Language :: Python :: 3
Classifier: Operating System :: OS Independent
Requires-Python: >=3.7
License-File: LICENSE
Requires-Dist: pyserial
Dynamic: author
Dynamic: author-email
Dynamic: classifier
Dynamic: home-page
Dynamic: license-file
Dynamic: requires-dist
Dynamic: requires-python
Dynamic: summary
